transimg.py
transimg-0.2.0.dist-info/LICENSE
transimg-0.2.0.dist-info/METADATA
transimg-0.2.0.dist-info/WHEEL
transimg-0.2.0.dist-info/entry_points.txt
transimg-0.2.0.dist-info/top_level.txt
transimg-0.2.0.dist-info/RECORD
